zoopy/__init__.py
zoopy/animal.py
zoopy/data.py
zoopy/exceptions.py
zoopy/models.py
zoopy/version.py
zoopy/viz.py
zoopy/datasets/animals_ru.csv
zoopy/datasets/imagenet_classes.txt
zoopy/templates/description.html
zoopy/templates/description.txt
zoopy-0.0.4.dist-info/METADATA
zoopy-0.0.4.dist-info/WHEEL
zoopy-0.0.4.dist-info/top_level.txt
zoopy-0.0.4.dist-info/RECORD
