Metadata-Version: 2.1
Name: zoopy
Version: 0.0.4
Summary: A Python library for animal data analysis
Home-page: https://github.com/droyti46/zoopy
Author: Nikita Bakutov
Author-email: nikitabakutov2008@gmail.com
License: MIT
Classifier: Programming Language :: Python :: 3
Classifier: License :: OSI Approved :: MIT License
Requires-Python: >=3.8
Requires-Dist: pandas>=2.2.0
Requires-Dist: matplotlib>=3.9.0
Requires-Dist: tqdm>=4.66.0
Requires-Dist: Levenshtein>=0.26.0
Requires-Dist: numpy>=1.26.4
Requires-Dist: torch>=2.4.0
Requires-Dist: torchvision>=0.19.0
